.gitignore
Dockerfile
LICENSE
MANIFEST.in
Makefile
README.md
docker-build.sh
docker-entrypoint.sh
setup.py
BlastRadius.egg-info/PKG-INFO
BlastRadius.egg-info/SOURCES.txt
BlastRadius.egg-info/dependency_links.txt
BlastRadius.egg-info/requires.txt
BlastRadius.egg-info/top_level.txt
bin/blast-radius
blastradius/__init__.py
blastradius/graph.py
blastradius/util.py
blastradius/handlers/__init__.py
blastradius/handlers/apply.py
blastradius/handlers/dot.py
blastradius/handlers/plan.py
blastradius/handlers/terraform.py
blastradius/server/__init__.py
blastradius/server/server.py
blastradius/server/static/css/bootstrap.min.css
blastradius/server/static/css/selectize.css
blastradius/server/static/css/style.css
blastradius/server/static/js/blast-radius.js
blastradius/server/static/js/bootstrap.min.js
blastradius/server/static/js/categories.js
blastradius/server/static/js/categories.json
blastradius/server/static/js/d3-tip.js
blastradius/server/static/js/d3.v4.js
blastradius/server/static/js/d3.v4.min.js
blastradius/server/static/js/fontawesome-all.min.js
blastradius/server/static/js/jquery.slim.min.js
blastradius/server/static/js/selectize.js
blastradius/server/static/js/svg-pan-zoom.js
blastradius/server/templates/error.html
blastradius/server/templates/index.html