Metadata-Version: 1.2
Name: BlastRadius
Version: 0.1.13
Summary: Interactive visualizations of Terraform dependency graphs
Home-page: http://pypi.python.org/pypi/BlastRadius/
Author: Patrick McMurchie
Author-email: patrick.mcmurchie@gmail.com
License: LICENSE.txt
Platform: UNKNOWN
Requires-Python: >=3.5.0
